modsim/__init__.py
modsim/__main__.py
modsim/main.py
modsim/utils.py
modsim-0.5.2.dist-info/LICENSE
modsim-0.5.2.dist-info/METADATA
modsim-0.5.2.dist-info/WHEEL
modsim-0.5.2.dist-info/entry_points.txt
modsim-0.5.2.dist-info/RECORD
