Metadata-Version: 2.1
Name: modsim
Version: 0.5.2
Summary: A Simple Modbus TCP Device Simulator used for modpoll tool
Home-page: https://github.com/gavinying/modsim
Author: Ying Shaodong
Author-email: helloysd@gmail.com
Requires-Python: >=3.8.2,<4.0
Classifier: Programming Language :: Python :: 3
Classifier: Programming Language :: Python :: 3.9
Classifier: Programming Language :: Python :: 3.10
Classifier: Programming Language :: Python :: 3.11
Classifier: Programming Language :: Python :: 3.12
Classifier: Programming Language :: Python :: 3.13
Requires-Dist: pymodbus (>=3.6.9,<3.7.0)
Project-URL: Documentation, https://gavinying.github.io/modsim/
Project-URL: Repository, https://github.com/gavinying/modsim
